{
    "features1": [
      {
        "icon": "clock",
        "title": "Dynamic Budgeting Interface",
        "api":"budgeting-interface"
      },
      {
        "icon": "chart-line",
        "title": "Forecasting Models",
        "api":"forcasting-model"
      },
      {
        "icon": "cog",
        "title": "Expense Categorization AI",
        "api":"exp-categorization"
      },
      {
        "icon": "sync-alt",
        "title": "Zero-based Budgeting AI Assistant",
        "api": "zero-budgeting"
      },
      {
        "icon": "chart-bar",
        "title": "Budget Health Metrics",
        "api":"health-metrics"
      },
      {
        "icon": "chart-area",
        "title": "Historical Budget Trends Analysis",
        "api": "trends-analysis"
      },
      {
        "icon": "bullhorn",
        "title": "Variable Expense Predictor",
        "api":"expense-predictor"
      },
      {
        "icon": "cube",
        "title": "What-If Scenario Planning",
        "api": "scenario-planning"
      }
    ],
    "features2": [
      {
        "icon": "credit-card",
        "title": "AI Savings Recommendations",
        "api":"savings-recommendation"
      },
      {
        "icon": "cog",
        "title": "Automated Investment Analysis",
        "api":"auto-investment"
      },
      {
        "icon": "home",
        "title": "Retirement Planning AI Advisor",
        "api":"retirement-plan"
      },
      {
        "icon": "people-carry",
        "title": "Goal-based Investment Allocation",
        "api":"goalbased-investment"
      },
      {
        "icon": "database",
        "title": "Risk Tolerance Assessment Tool",
        "api":"risk-tool"
      },
      {
        "icon": "star",
        "title": "Savings Milestone Tracker",
        "api":"milestone-tracker"
      },
      {
        "icon": "wifi",
        "title": "Educational Investment Content",
        "api":"education-investment"
      },
      {
        "icon": "arrow-up",
        "title": "Market Trend AI Analysis",
        "api":"market-trend"
      }
    ],

    "features3": [
      {
        "icon": "grip-lines",
        "title": "Trend Line"
      },
      {
        "icon": "seedling",
        "title": "Ray"
      },
      {
        "icon": "lines-leaning",
        "title": "Info Line"
      },
      {
        "icon": "line-height",
        "title": "Extended Line"
      },
      {
        "icon": "scalpel-line-dashed",
        "title": "Trend Angle"
      },
      {
        "icon": "arrow-right-long-to-line",
        "title": "Horizatal Line"
      },
      {
        "icon": "chart-line",
        "title": "Horizatal Ray"
      },
      {
        "icon": "arrow-up-from-dotted-line",
        "title": "Vertical Line"
      },
      {
        "icon": "draw-polygon",
        "title": "Cross Line"
      }
    ],

    "features4": [
      {
        "icon": "olive-branch",
        "title": "Fib Retracement"
      },
      {
        "icon": "sterling-sign",
        "title": "Trend-based Fib Retracement"
      },
      {
        "icon": "satellite",
        "title": "Fib Channel"
      },
      {
        "icon": "hand-spock",
        "title": "Fib Time Zone"
      },
      {
        "icon": "star-of-life",
        "title": "Fib Speed Resistance Fan"
      },
      {
        "icon": "anchor",
        "title": "Trend Based Fib Time"
      },
      {
        "icon": "mandolin",
        "title": "Fib Circles"
      },
      {
        "icon": "galaxy",
        "title": "Fib Spiral"
      },
      {
        "icon": "cheese",
        "title": "Fib Wedge"
      },
      {
        "icon": "ruler",
        "title": "PitchFan"
      }

    ]

  }